__init__.py
ksux/__init__.py
ksux/__main__.py
ksux/src/create_manifests.py
ksux/src/patch.py
ksux/src/read_file.py
ksux/src/save_manifests.py
ksux/src/schemas.py
ksux/tests/__init__.py
ksux/tests/config.py
ksux/tests/test_patch.py
ksux/tests/test_read_file.py
ksux-0.7.0.dist-info/LICENSE
ksux-0.7.0.dist-info/METADATA
ksux-0.7.0.dist-info/WHEEL
ksux-0.7.0.dist-info/entry_points.txt
ksux-0.7.0.dist-info/top_level.txt
ksux-0.7.0.dist-info/RECORD
