Metadata-Version: 2.1
Name: ksux
Version: 0.7.0
Summary: Easy customization of kubernetes manifests
Author: Tomas Sladecek
License: MIT License
Project-URL: Homepage, https://github.com/tsladecek/ksux
Classifier: Programming Language :: Python :: 3
Classifier: Operating System :: OS Independent
Requires-Python: >=3.12
License-File: LICENSE
Requires-Dist: pydantic <3,>2
Requires-Dist: ruamel.yaml <1,>=0.17.21
